repurp/__init__.py
repurp/platform_specs.py
repurp/repurp.py
repurp/use_cli.py
repurp-0.2.0.dist-info/METADATA
repurp-0.2.0.dist-info/WHEEL
repurp-0.2.0.dist-info/entry_points.txt
repurp-0.2.0.dist-info/licenses/LICENSE
repurp-0.2.0.dist-info/RECORD
