Metadata-Version: 2.3
Name: repurp
Version: 0.2.0
Summary: Repurpose videos for various social media platforms with optimized settings
Project-URL: Homepage, https://github.com/nwaughachukwuma/repurp
Project-URL: Repository, https://github.com/nwaughachukwuma/repurp
Project-URL: Issues, https://github.com/nwaughachukwuma/repurp/issues
Author-email: Chukwuma Nwaugha <chuks@veedo.ai>
License: MIT
License-File: LICENSE
Keywords: ffmpeg reformat video,instagram video,repurpose video,social media videos,tiktok video,twitter video
Classifier: Environment :: Console
Classifier: Environment :: GPU
Classifier: Environment :: Web Environment
Classifier: License :: OSI Approved :: MIT License
Classifier: Operating System :: OS Independent
Classifier: Programming Language :: Python :: 3
Classifier: Topic :: Internet :: WWW/HTTP :: Dynamic Content
Classifier: Topic :: Multimedia :: Video
Classifier: Topic :: Software Development :: Libraries :: Python Modules
Requires-Python: >=3.8
